[
  {
    "CPU": "Intel(R) Core(TM) i7-8550U CPU @ 1.80GHz",
    "OS": "Windows 10",
    "cores": 8,
    "score": 78,
    "clock": 156185700,
    "ram": 17033633792
  },
  {
    "CPU": "Intel(R) Core(TM) i7-8550U CPU @ 1.80GHz",
    "OS": "Windows 10",
    "cores": 8,
    "score": 136,
    "clock": 272190200,
    "ram": 17033633792
  },
  {
    "CPU": "Intel(R) Core(TM) i7-8550U CPU @ 1.80GHz",
    "OS": "Windows 10",
    "cores": 8,
    "score": 87,
    "clock": 174584800,
    "ram": 17033633792
  },
  {
    "CPU": "Intel(R) Core(TM) i7-8550U CPU @ 1.80GHz",
    "OS": "Windows 10",
    "cores": 8,
    "score": 75,
    "clock": 151735500,
    "ram": 17033633792
  },
  {
    "CPU": "Intel(R) Core(TM) i7-8550U CPU @ 1.80GHz",
    "OS": "Windows 10",
    "cores": 8,
    "score": 201,
    "clock": 403812500,
    "ram": 17033633792
  },
  {
    "CPU": "Intel(R) Core(TM) i7-8550U CPU @ 1.80GHz",
    "OS": "Windows 10",
    "cores": 8,
    "score": 93,
    "clock": 186893000,
    "ram": 17033633792
  },
  {
    "CPU": "Intel(R) Core(TM) i7-8550U CPU @ 1.80GHz",
    "OS": "Windows 10",
    "cores": 8,
    "score": 106,
    "clock": 212076500,
    "ram": 17033633792
  },
  {
    "CPU": "Intel(R) Core(TM) i7-8550U CPU @ 1.80GHz",
    "OS": "Windows 10",
    "cores": 8,
    "score": 95,
    "clock": 191268000,
    "ram": 17033633792
  },
  {
    "CPU": "Intel(R) Core(TM) i7-8550U CPU @ 1.80GHz",
    "OS": "Windows 10",
    "cores": 8,
    "score": 84,
    "clock": 168766200,
    "ram": 17033633792
  },
  {
    "CPU": "Intel(R) Core(TM) i7-8550U CPU @ 1.80GHz",
    "OS": "Windows 10",
    "cores": 8,
    "score": 125,
    "clock": 251536100,
    "ram": 17033633792
  },
  {
    "CPU": "Intel(R) Core(TM) i7-8550U CPU @ 1.80GHz",
    "OS": "Windows 10",
    "cores": 8,
    "score": 78,
    "clock": 157658100,
    "ram": 17033633792
  },
  {
    "CPU": "Intel(R) Core(TM) i7-8550U CPU @ 1.80GHz",
    "OS": "Windows 10",
    "cores": 8,
    "score": 85,
    "clock": 170391300,
    "ram": 17033633792
  },
  {
    "CPU": "Intel(R) Core(TM) i7-8550U CPU @ 1.80GHz",
    "OS": "Windows 10",
    "cores": 8,
    "score": 147,
    "clock": 294901000,
    "ram": 17033633792
  },
  {
    "CPU": "Intel(R) Core(TM) i7-8550U CPU @ 1.80GHz",
    "OS": "Windows 10",
    "cores": 8,
    "score": 83,
    "clock": 167739900,
    "ram": 17033633792
  },
  {
    "CPU": "Intel(R) Core(TM) i7-8550U CPU @ 1.80GHz",
    "OS": "Windows 10",
    "cores": 8,
    "score": 2927,
    "clock": 5855283300,
    "ram": 17033633792
  },
  {
    "CPU": "Intel(R) Core(TM) i7-8550U CPU @ 1.80GHz",
    "OS": "Windows 10",
    "cores": 8,
    "score": 767,
    "clock": 3836425800,
    "ram": 17033633792
  },
  {
    "CPU": "Intel(R) Core(TM) i7-8550U CPU @ 1.80GHz",
    "OS": "Windows 10",
    "cores": 8,
    "score": 27,
    "clock": 244931500,
    "ram": 17033633792
  },
  {
    "CPU": "Intel(R) Core(TM) i7-8550U CPU @ 1.80GHz",
    "OS": "Windows 10",
    "cores": 8,
    "score": 1089,
    "clock": 7084175300,
    "ram": 17033633792
  },
  {
    "CPU": "Intel(R) Core(TM) i7-8550U CPU @ 1.80GHz",
    "OS": "Windows 10",
    "cores": 8,
    "score": 1085,
    "clock": 5426027000,
    "ram": 17033633792
  },
  {
    "CPU": "Intel(R) Core(TM) i7-8550U CPU @ 1.80GHz",
    "OS": "Windows 10",
    "cores": 8,
    "score": 13906,
    "clock": 6953063000,
    "ram": 17033633792
  },
  {
    "CPU": "Intel(R) Core(TM) i7-8550U CPU @ 1.80GHz",
    "OS": "Windows 10",
    "cores": 8,
    "score": 1381,
    "clock": 8288891900,
    "ram": 17033633792
  },
  {
    "CPU": "Intel(R) Core(TM) i7-8550U CPU @ 1.80GHz",
    "OS": "Windows 10",
    "cores": 8,
    "score": 561,
    "clock": 3928620500,
    "ram": 17033633792
  },
  {
    "CPU": "Intel(R) Core(TM) i7-8550U CPU @ 1.80GHz",
    "OS": "Windows 10",
    "cores": 8,
    "score": 1125,
    "clock": 8440208200,
    "ram": 17033633792
  },
  {
    "CPU": "Intel(R) Core(TM) i7-8550U CPU @ 1.80GHz",
    "OS": "Windows 10",
    "cores": 8,
    "score": 871,
    "clock": 6972654600,
    "ram": 17033633792
  },
  {
    "CPU": "Intel(R) Core(TM) i7-8550U CPU @ 1.80GHz",
    "OS": "Windows 10",
    "cores": 8,
    "score": 971,
    "clock": 8259074300,
    "ram": 17033633792
  },
  {
    "CPU": "Intel(R) Core(TM) i7-8550U CPU @ 1.80GHz",
    "OS": "Windows 10",
    "cores": 8,
    "score": 940,
    "clock": 8464136300,
    "ram": 17033633792
  },
  {
    "CPU": "Intel(R) Core(TM) i7-8550U CPU @ 1.80GHz",
    "OS": "Windows 10",
    "cores": 8,
    "score": 92,
    "clock": 8367119000,
    "ram": 17033633792
  },
  {
    "CPU": "Intel(R) Core(TM) i7-8550U CPU @ 1.80GHz",
    "OS": "Windows 10",
    "cores": 8,
    "score": 45,
    "clock": 4091007400,
    "ram": 17033633792
  }
]